attainia_django_extensions/__init__.py
attainia_django_extensions/__version__.py
attainia_django_extensions/models.py
attainia_django_extensions/utils.py
attainia_django_extensions/jwt/__init__.py
attainia_django_extensions/jwt/jwt_authentication.py
attainia_django_extensions/jwt/jwt_scope_permissions.py
attainia_django_extensions/rpc/__init__.py
attainia_django_extensions/rpc/event_handler_decorator.py
attainia_django_extensions/rpc/rpc_decorator.py
attainia_django_extensions/rpc/rpc_drf.py
attainia_django_extensions/rpc/rpc_errors.py
attainia_django_extensions/rpc/rpc_mixin.py
attainia_django_extensions/rpc/rpc_view.py
attainia_django_extensions-0.6.1.dist-info/DESCRIPTION.rst
attainia_django_extensions-0.6.1.dist-info/METADATA
attainia_django_extensions-0.6.1.dist-info/RECORD
attainia_django_extensions-0.6.1.dist-info/WHEEL
attainia_django_extensions-0.6.1.dist-info/metadata.json
attainia_django_extensions-0.6.1.dist-info/top_level.txt
