Metadata-Version: 2.0
Name: attainia-django-extensions
Version: 0.6.1
Summary: A collection of helpful utilities to be used in Attainia Django/Rest Framework projects
Home-page: https://github.com/Attainia/attainia-django-extensions
Author: Attainia
Author-email: developers@attainia.com
License: MIT
Platform: UNKNOWN
Classifier: License :: OSI Approved :: MIT License
Classifier: Programming Language :: Python
Classifier: Programming Language :: Python :: 3
Classifier: Programming Language :: Python :: 3.3
Classifier: Programming Language :: Python :: 3.4
Classifier: Programming Language :: Python :: 3.5
Classifier: Programming Language :: Python :: 3.6
Classifier: Programming Language :: Python :: Implementation :: CPython
Classifier: Programming Language :: Python :: Implementation :: PyPy
Requires-Dist: django
Requires-Dist: djangorestframework
Requires-Dist: cid
Requires-Dist: django-nameko
